aws_sessions_switcher/__init__.py
aws_sessions_switcher/argument_parser.py
aws_sessions_switcher/aws_client.py
aws_sessions_switcher/config_collector.py
aws_sessions_switcher/config_parser_util.py
aws_sessions_switcher/util.py
config/__init__.py
config/__version__.py
config/config.py
aws_sessions_switcher-0.0.16.dist-info/LICENSE
aws_sessions_switcher-0.0.16.dist-info/METADATA
aws_sessions_switcher-0.0.16.dist-info/WHEEL
aws_sessions_switcher-0.0.16.dist-info/entry_points.txt
aws_sessions_switcher-0.0.16.dist-info/top_level.txt
aws_sessions_switcher-0.0.16.dist-info/RECORD
