Metadata-Version: 2.1
Name: aws-sessions-switcher
Version: 0.0.16
Summary: A tool to help switching between multiple AWS environments easy and seamless
Home-page: https://github.com/DEV-BALAN-JAYAVICTOR/aws-sessions-switcher
Author: Balan Jayavictor
Author-email: dev.balan.jayavictor@gmail.com
License: UNKNOWN
Platform: UNKNOWN
Classifier: Programming Language :: Python :: 3
Classifier: License :: OSI Approved :: MIT License
Classifier: Operating System :: OS Independent
Requires-Python: >=3.5
Requires-Dist: configparser (>=5.0.0)
Requires-Dist: boto3 (>=1.13.24)
Requires-Dist: InquirerPy (>=0.3)
Requires-Dist: dataclasses (<0.6,>=0.1)
Requires-Dist: argcomplete (<2,>=1.11.1)
Requires-Dist: prettytable (<3.5.0,>=1)
Requires-Dist: prompt-toolkit (>=3)
